vzucher_de_toolkit/__init__.py
vzucher_de_toolkit/main.py
vzucher_de_toolkit/tests/__init__.py
vzucher_de_toolkit/vm.py
vzucher_de_toolkit-0.1.0.dist-info/METADATA
vzucher_de_toolkit-0.1.0.dist-info/WHEEL
vzucher_de_toolkit-0.1.0.dist-info/entry_points.txt
vzucher_de_toolkit-0.1.0.dist-info/RECORD
